pytorch_dragon/__init__.py
pytorch_dragon/pytorch_dragon.py
pytorch_dragon/acquisition/__init__.py
pytorch_dragon/acquisition/functions.py
pytorch_dragon/backprop/__init__.py
pytorch_dragon/backprop/grad_accumulator.py
pytorch_dragon/backprop/grad_clipping.py
pytorch_dragon/backprop/regularization.py
pytorch_dragon/search/__init__.py
pytorch_dragon/search/continuous_search.py
pytorch_dragon/search/hyperparam.py
pytorch_dragon/search/models/__init__.py
pytorch_dragon/search/models/bopt_models.py
pytorch_dragon/tools/__init__.py
pytorch_dragon/tools/logging.py
pytorch_dragon/tools/memory.py
pytorch_dragon/tools/pruning.py
pytorch_dragon/tools/replay.py
pytorch_dragon/tools/trainer.py
pytorch_dragon/tools/vision.py
pytorch_dragon/utils/__init__.py
pytorch_dragon/utils/metrics.py
pytorch_dragon/utils/system.py
pytorch_dragon/utils/torch_utils.py
pytorch_dragon-0.2.4.dist-info/LICENSE
pytorch_dragon-0.2.4.dist-info/METADATA
pytorch_dragon-0.2.4.dist-info/WHEEL
pytorch_dragon-0.2.4.dist-info/top_level.txt
pytorch_dragon-0.2.4.dist-info/RECORD
